pyxodr/__init__.py
pyxodr/geometries/__init__.py
pyxodr/geometries/_standard_spiral.py
pyxodr/geometries/arc.py
pyxodr/geometries/base.py
pyxodr/geometries/cubic_polynom.py
pyxodr/geometries/multi.py
pyxodr/geometries/spiral.py
pyxodr/road_objects/__init__.py
pyxodr/road_objects/junction.py
pyxodr/road_objects/lane.py
pyxodr/road_objects/lane_section.py
pyxodr/road_objects/network.py
pyxodr/road_objects/road.py
pyxodr/utils/__init__.py
pyxodr/utils/array.py
pyxodr/utils/cached_property.py
pyxodr/utils/curved_text.py
pyxodr-0.1.3.dist-info/LICENSE.md
pyxodr-0.1.3.dist-info/METADATA
pyxodr-0.1.3.dist-info/WHEEL
pyxodr-0.1.3.dist-info/top_level.txt
pyxodr-0.1.3.dist-info/RECORD
